{
  "project_info": {
    "project_number": "184042537896",
    "firebase_url": "https://reactbs-dcb4c.firebaseio.com",
    "project_id": "reactbs-dcb4c",
    "storage_bucket": "reactbs-dcb4c.appspot.com"
  },
  "client": [
    {
      "client_info": {
        "mobilesdk_app_id": "1:184042537896:android:c1c191c2b93ea432",
        "android_client_info": {
          "package_name": "com.wizardscompanion"
        }
      },
      "oauth_client": [
        {
          "client_id": "184042537896-hposkssfh6upqlq75decnc5n59csd4qm.apps.googleusercontent.com",
          "client_type": 3
        }
      ],
      "api_key": [
        {
          "current_key": "AIzaSyAugs9v_F_VQQPZv2GR6LY_igg2KMbZNCI"
        }
      ],
      "services": {
        "analytics_service": {
          "status": 1
        },
        "appinvite_service": {
          "status": 1,
          "other_platform_oauth_client": []
        },
        "ads_service": {
          "status": 2
        }
      }
    }
  ],
  "configuration_version": "1"
}